Workbook

Sheet README
A1: Peak Cluster Feedstock De-Risking Model
A2: Oxy-fuel + Waste Heat Recovery vs. Baseline Amine Capture — CapEx/OpEx trade-off calculator
A3: Built for: Peak District cement/lime quarry sites feeding the Peak Cluster CO2 pipeline
A5: PURPOSE
A6: This model quantifies the operating-cost case for treating flue gas with oxy-fuel combustion + waste heat recovery (WHR) + BESS load-shifting, INSTEAD OF conventional amine scrubbing, before compressing CO2 into the Peak Cluster pipeline. It does not model an alternative to the pipeline — it assumes the pipeline is built and asks: which on-site pre-treatment package is cheaper to feed it.
A8: HOW TO USE
A9: 1. Edit only the blue cells on the 'Assumptions' tab — these are the levers.
A10: 2. 'Baseline' and 'Optimized' tabs calculate each pathway automatically from those assumptions.
A11: 3. 'Comparison' tab shows capex delta, opex savings and simple payback.
A12: 4. 'Sensitivity' tab stress-tests the two least certain inputs: electricity tariff / flue gas dilution, and the oxy-fuel O2 demand ratio / ASU efficiency.
A14: CONFIDENCE LEVELS — READ BEFORE PRESENTING THIS EXTERNALLY
A15: HIGH confidence (published benchmarks, cited on Assumptions tab): CO2 compression energy, amine reboiler duty, cryogenic ASU specific energy, ORC capex, UK ETS price, UK industrial electricity tariff range.
... A35: - All results are nominal (today's £), not inflation-adjusted; a real discount rate is used to annualize capex.

Sheet Assumptions
A1: Assumptions
A2: Edit only the blue values in column B. UPDATED for Hope Cement Works (Breedon, Derbyshire) — see notes in column D for what changed and why. O2 ratio and oxy-fuel retrofit capex (rows 32/36) remain unresolved placeholders.
A4: Parameter | B4: Value | C4: Unit | D4: Source / Confidence
A6: SITE & TARGET
A7: Kiln thermal rating | B7: 140 | C7: MWth | D7: MEDIUM — calculated estimate: 1.5Mt cement/yr x ~0.85 clinker ratio x 3.2 GJ/t (precalciner benchmark) / 8,000 op-hrs. NOT a confirmed nameplate figure — Breedon/EA haven't published kiln MWth.
A8: Target annual CO2 to pipeline | B8: 1200000 | C8: t/yr | D8: HIGH — Hope Valley Climate Action: Hope Cement Works is "by far the largest emitter of greenhouse gases in the Hope Valley", ~1.2Mt CO2/yr
A9: Baseline flue gas CO2 concentration | B9: 0.2 | C9: % | D9: MEDIUM — sourcing-table proxy for CEMENT kilns specifically (18-22%); Hope is cement-only, no lime co-production, so the 25-35% lime proxy doesn't apply here
A10: Oxy-fuel flue gas CO2 concentration achieved | B10: 0.85 | C10: % | D10: Oxy-fuel retrofit pushes CO2 >80% (CEMCAP)
A11: Reference CO2% used to scale amine energy penalty | B11: 0.2 | C11: % | D11: Modelling reference point — see README simplifications
A13: PRICES
A14: Grid electricity tariff | B14: 100 | C14: £/MWh | D14: MEDIUM — UK large industrial users ~86-240 £/MWh (Supercharger to standard large-fixed); site-specific contract needed
A15: Thermal (steam) energy cost | B15: 35 | C15: £/MWh-th | D15: MEDIUM — placeholder gas-fired steam cost, cheaper than grid electricity
A16: UK ETS price (2026 civil penalty rate) | B16: 49.41 | C16: £/t CO2 | D16: HIGH — UK ETS Authority 2026 published rate; market range £30-60
A18: FINANCE
A19: Discount rate | B19: 0.08 | C19: % | D19: Placeholder WACC — replace with site-specific hurdle rate
A20: Plant/asset life | B20: 20 | C20: years | D20: Typical industrial capital asset life
A22: SHARED — CO2 COMPRESSION (both pathways need this)
A23: Compression energy to pipeline spec (~90-110 bar) | B23: 105 | C23: kWh/t CO2 | D23: HIGH — standard CCS benchmark range 90-120 kWh/t
A25: BASELINE — AMINE CAPTURE
A26: Amine reboiler (thermal) duty, at reference CO2% | B26: 900 | C26: kWh-th/t CO2 | D26: HIGH — typical MEA ~3.0-3.5 GJ/t CO2 (~830-970 kWh-th/t)
A27: Amine electrical auxiliary load (pumps/fans) | B27: 40 | C27: kWh/t CO2 | D27: HIGH — typical amine plant benchmark
A28: Amine plant capex | B28: 320 | C28: £/tpa capacity | D28: MEDIUM — real-world benchmark ~$400/Tpa (Thunder Said Energy), converted @ ~£0.80/$
A29: Amine non-energy opex (solvent, maintenance, labour) | B29: 8 | C29: £/t CO2 | D29: LOW / placeholder — needs site-specific quote
A31: OPTIMIZED — OXY-FUEL + AIR SEPARATION UNIT (ASU)
A32: O2 demand ratio | B32: 0.3 | C32: t O2 / t CO2 captured | D32: MEDIUM — simplified industry rule of thumb; needs mass-balance/engineering study
A33: ASU specific energy | B33: 300 | C33: kWh/t O2 | D33: HIGH — modern cryogenic ASU realistic range 250-500 kWh/t (theoretical min 51 kWh/t)
A34: ASU capex | B34: 160 | C34: £/tpa O2 capacity | D34: MEDIUM — benchmark ~$200/Tpa O2 (Thunder Said Energy), converted @ ~£0.80/$
A35: Pipeline-spec purification/drying energy | B35: 30 | C35: kWh/t CO2 | D35: LOW / placeholder — removal of residual N2, moisture, SOx/NOx traces
A36: Oxy-fuel kiln/burner retrofit capex | B36: 40 | C36: £/tpa CO2 capacity | D36: LOW / placeholder — CEMCAP tested components only at 30-500 kWth pilot scale; no commercial retrofit benchmark exists yet
A37: Oxy-fuel non-energy opex | B37: 5 | C37: £/t CO2 | D37: LOW / placeholder — needs site-specific quote
A39: OPTIMIZED — WASTE HEAT RECOVERY (ORC)
A40: Recoverable waste heat | B40: 0.35 | C40: % of kiln thermal input | D40: HIGH — cement industry reports 30-40% of kiln/clinker-cooler heat wasted pre-WHR
A41: ORC electrical conversion efficiency | B41: 0.18 | C41: % | D41: MEDIUM — typical ORC thermal-to-electric efficiency at cement exhaust temperatures
A42: ORC capex | B42: 2000000 | C42: £/MWe installed | D42: HIGH — benchmark $1.8-3.2M/MWe (industry WHR cost surveys), converted @ ~£0.80/$
A43: Kiln operating hours | B43: 8000 | C43: hrs/yr | D43: Typical continuous kiln operation (~91% capacity factor)
A45: OPTIMIZED — BESS (GRID-QUEUE BYPASS)
A46: BESS capex | B46: 280 | C46: £/kWh installed | D46: MEDIUM — UK commercial/industrial BESS range £200-450/kWh (2025-26)
A47: BESS power rating | B47: 10 | C47: MW | D47: User input — sized to shift ASU/compression peak load off the DNO connection
A48: BESS duration | B48: 4 | C48: hours | D48: User input
A49: Avoided/delayed grid reinforcement value | B49: 3000000 | C49: £ | D49: LOW / placeholder — needs DNO quote; values the multi-year queue risk avoided (see prior red-team review)

Sheet Baseline
A1: Baseline — Amine Capture
A2: Conventional amine scrubbing of as-is (dilute) flue gas, then compression to pipeline spec.
A4: Metric | B4: Value | C4: Unit | D4: Note
A6: Annual CO2 volume | B6: =Assumptions!$B$8 | C6: t/yr
A7: Amine reboiler duty, adjusted for actual flue gas CO2% | B7: =Assumptions!$B$26*(Assumptions!$B$11/Assumptions!$B$9) | C7: kWh-th/t CO2 | D7: Scaled vs 20% reference — more dilute gas needs more solvent circulation per t CO2
A8: Thermal energy cost | B8: =B7*Assumptions!$B$15/1000 | C8: £/t CO2
A9: Electrical load (amine aux + compression) | B9: =Assumptions!$B$27+Assumptions!$B$23 | C9: kWh/t CO2
A10: Electrical cost | B10: =B9*Assumptions!$B$14/1000 | C10: £/t CO2
A11: Non-energy opex (solvent, maintenance, labour) | B11: =Assumptions!$B$29 | C11: £/t CO2
A12: Total opex | B12: =B8+B10+B11 | C12: £/t CO2
A13: Annual opex | B13: =B12*B6 | C13: £/yr
A15: CAPEX & LEVELIZATION
A16: Capex | B16: =Assumptions!$B$28*B6 | C16: £
A17: Capital recovery factor (CRF) | B17: =(Assumptions!$B$19*(1+Assumptions!$B$19)^Assumptions!$B$20)/((1+Assumptions!$B$19)^Assumptions!$B$20-1)
A18: Annualized capex | B18: =B16*B17 | C18: £/yr
A19: Levelized capex | B19: =B18/B6 | C19: £/t CO2
A20: ALL-IN LEVELIZED COST | B20: =B12+B19 | C20: £/t CO2

Sheet Optimized
A1: Optimized — Oxy-Fuel + ASU + Waste Heat Recovery + BESS
A2: Oxy-fuel combustion concentrates the CO2 stream (>80%); waste heat recovery self-generates power for the ASU/compression load; BESS shifts the residual load off the DNO connection.
A4: Metric | B4: Value | C4: Unit | D4: Note
A6: Annual CO2 volume | B6: =Assumptions!$B$8 | C6: t/yr
A7: ELECTRICAL LOAD
A8: O2 required | B8: =Assumptions!$B$32*B6 | C8: t/yr
A9: ASU electrical intensity | B9: =Assumptions!$B$32*Assumptions!$B$33 | C9: kWh/t CO2
A10: Pipeline-spec purification/drying | B10: =Assumptions!$B$35 | C10: kWh/t CO2
A11: Compression to pipeline spec | B11: =Assumptions!$B$23 | C11: kWh/t CO2
A12: Total electrical demand | B12: =B9+B10+B11 | C12: kWh/t CO2
A13: Total electrical demand | B13: =B12*B6/1000 | C13: MWh/yr
A15: WASTE HEAT RECOVERY (SELF-GENERATION)
A16: Recoverable waste heat | B16: =Assumptions!$B$7*Assumptions!$B$40 | C16: MWth
A17: WHR electrical output (ORC) | B17: =B16*Assumptions!$B$41 | C17: MWe
A18: Annual WHR generation | B18: =B17*Assumptions!$B$43 | C18: MWh/yr
A19: Net grid electricity required | B19: =MAX(0,B13-B18) | C19: MWh/yr
A20: Share of load covered by self-generated WHR power | B20: =MIN(1,B18/B13) | C20: %
A22: OPEX
A23: Grid electricity cost | B23: =B19*Assumptions!$B$14 | C23: £/yr
A24: Non-energy opex (oxy-fuel line) | B24: =Assumptions!$B$37*B6 | C24: £/yr
A25: Total opex | B25: =B23+B24 | C25: £/yr
A26: Total opex | B26: =B25/B6 | C26: £/t CO2
A28: CAPEX & LEVELIZATION
A29: ASU capex | B29: =Assumptions!$B$34*B8 | C29: £
A30: Oxy-fuel kiln/burner retrofit capex | B30: =Assumptions!$B$36*B6 | C30: £
A31: ORC capex | B31: =B17*Assumptions!$B$42 | C31: £
A32: BESS capex | B32: =Assumptions!$B$47*Assumptions!$B$48*1000*Assumptions!$B$46 | C32: £
A33: Total capex before grid-reinforcement offset | B33: =B29+B30+B31+B32 | C33: £
A34: Avoided/delayed grid-reinforcement value | B34: =Assumptions!$B$49 | C34: £
A35: Net capex | B35: =B33-B34 | C35: £
A36: Capital recovery factor (CRF) | B36: =Baseline!B17
A37: Annualized capex | B37: =B35*B36 | C37: £/yr
A38: Levelized capex | B38: =B37/B6 | C38: £/t CO2
A39: ALL-IN LEVELIZED COST | B39: =B26+B38 | C39: £/t CO2

Sheet Comparison
A1: Comparison — Baseline (Amine) vs Optimized (Oxy-Fuel + WHR + BESS)
A2: Both pathways feed the same Peak Cluster pipeline. This asks which is cheaper to build and run, not whether to build the pipeline.
A4: Metric | B4: Value | C4: Unit | D4: Note
A6: ALL-IN LEVELIZED COST
A7: Baseline (amine) — all-in £/t | B7: =Baseline!$B$20 | C7: £/t CO2
A8: Optimized (oxy-fuel+WHR+BESS) — all-in £/t | B8: =Optimized!$B$39 | C8: £/t CO2
A9: Savings per tonne | B9: =B7-B8 | C9: £/t CO2
A10: Savings, % | B10: =B9/B7 | C10: %
A11: UK ETS price (reference only) | B11: =Assumptions!$B$16 | C11: £/t CO2 | D11: Both pathways still need to run — ETS is the cost of NOT capturing, not an alternative to either pathway
A13: CAPEX
A14: Baseline (amine) capex | B14: =Baseline!$B$16 | C14: £
A15: Optimized net capex (after grid-reinforcement offset) | B15: =Optimized!$B$35 | C15: £
A16: Capex delta (Optimized − Baseline) | B16: =B15-B14 | C16: £
A18: ANNUAL OPEX
A19: Baseline (amine) annual opex | B19: =Baseline!$B$13 | C19: £/yr
A20: Optimized annual opex | B20: =Optimized!$B$25 | C20: £/yr
A21: Annual opex savings | B21: =B19-B20 | C21: £/yr
A23: PAYBACK
A24: Simple payback | B24: =IF(B16<=0,0,B16/B21) | C24: years
A25: Verdict | B25: =IF(B16<=0,"Optimized package has LOWER capex AND lower opex — dominant, no payback needed","Positive incremental capex — see payback years above")
A27: WHAT THE OXY-FUEL PACKAGE IS INSULATING YOU FROM
A28: Share of optimized-case electrical load covered by self-generated WHR power | B28: =Optimized!$B$20 | C28: % | D28: Higher = less exposure to wholesale tariff volatility and DNO grid-queue risk

Sheet Sensitivity
A1: Sensitivity
A2: Stress-tests the two least certain assumption groups against the headline savings/cost figures.
A4: TABLE 1 — Savings £/t (Baseline − Optimized) vs electricity tariff and baseline flue gas CO2%
A5: Tariff \ CO2% | B5: 0.14 | C5: 0.16 | D5: 0.18 | E5: 0.2 | F5: 0.22 | G5: 0.25
A6: 60 | B6: =(((Assumptions!$B$26*(Assumptions!$B$11/B$5))*Assumptions!$B$15/1000+(Assumptions!$B$27+Assumptions!$B$23)*$A6/1000+Assumptions!$B$29)+Baseline!$B$19)-((Optimized!$B$19*$A6)/Optimized!$B$6+Assumptions!$B$37+Optimized!$B$38) | C6: =(((Assumptions!$B$26*(Assumptions!$B$11/C$5))*Assumptions!$B$15/1000+(Assumptions!$B$27+Assumptions!$B$23)*$A6/1000+Assumptions!$B$29)+Baseline!$B$19)-((Optimized!$B$19*$A6)/Optimized!$B$6+Assumptions!$B$37+Optimized!$B$38) | D6: =(((Assumptions!$B$26*(Assumptions!$B$11/D$5))*Assumptions!$B$15/1000+(Assumptions!$B$27+Assumptions!$B$23)*$A6/1000+Assumptions!$B$29)+Baseline!$B$19)-((Optimized!$B$19*$A6)/Optimized!$B$6+Assumptions!$B$37+Optimized!$B$38) | E6: =(((Assumptions!$B$26*(Assumptions!$B$11/E$5))*Assumptions!$B$15/1000+(Assumptions!$B$27+Assumptions!$B$23)*$A6/1000+Assumptions!$B$29)+Baseline!$B$19)-((Optimized!$B$19*$A6)/Optimized!$B$6+Assumptions!$B$37+Optimized!$B$38) | F6: =(((Assumptions!$B$26*(Assumptions!$B$11/F$5))*Assumptions!$B$15/1000+(Assumptions!$B$27+Assumptions!$B$23)*$A6/1000+Assumptions!$B$29)+Baseline!$B$19)-((Optimized!$B$19*$A6)/Optimized!$B$6+Assumptions!$B$37+Optimized!$B$38) | G6: =(((Assumptions!$B$26*(Assumptions!$B$11/G$5))*Assumptions!$B$15/1000+(Assumptions!$B$27+Assumptions!$B$23)*$A6/1000+Assumptions!$B$29)+Baseline!$B$19)-((Optimized!$B$19*$A6)/Optimized!$B$6+Assumptions!$B$37+Optimized!$B$38)
A7: 80 | B7: =(((Assumptions!$B$26*(Assumptions!$B$11/B$5))*Assumptions!$B$15/1000+(Assumptions!$B$27+Assumptions!$B$23)*$A7/1000+Assumptions!$B$29)+Baseline!$B$19)-((Optimized!$B$19*$A7)/Optimized!$B$6+Assumptions!$B$37+Optimized!$B$38) | C7: =(((Assumptions!$B$26*(Assumptions!$B$11/C$5))*Assumptions!$B$15/1000+(Assumptions!$B$27+Assumptions!$B$23)*$A7/1000+Assumptions!$B$29)+Baseline!$B$19)-((Optimized!$B$19*$A7)/Optimized!$B$6+Assumptions!$B$37+Optimized!$B$38) | D7: =(((Assumptions!$B$26*(Assumptions!$B$11/D$5))*Assumptions!$B$15/1000+(Assumptions!$B$27+Assumptions!$B$23)*$A7/1000+Assumptions!$B$29)+Baseline!$B$19)-((Optimized!$B$19*$A7)/Optimized!$B$6+Assumptions!$B$37+Optimized!$B$38) | E7: =(((Assumptions!$B$26*(Assumptions!$B$11/E$5))*Assumptions!$B$15/1000+(Assumptions!$B$27+Assumptions!$B$23)*$A7/1000+Assumptions!$B$29)+Baseline!$B$19)-((Optimized!$B$19*$A7)/Optimized!$B$6+Assumptions!$B$37+Optimized!$B$38) | F7: =(((Assumptions!$B$26*(Assumptions!$B$11/F$5))*Assumptions!$B$15/1000+(Assumptions!$B$27+Assumptions!$B$23)*$A7/1000+Assumptions!$B$29)+Baseline!$B$19)-((Optimized!$B$19*$A7)/Optimized!$B$6+Assumptions!$B$37+Optimized!$B$38) | G7: =(((Assumptions!$B$26*(Assumptions!$B$11/G$5))*Assumptions!$B$15/1000+(Assumptions!$B$27+Assumptions!$B$23)*$A7/1000+Assumptions!$B$29)+Baseline!$B$19)-((Optimized!$B$19*$A7)/Optimized!$B$6+Assumptions!$B$37+Optimized!$B$38)
A8: 100 | B8: =(((Assumptions!$B$26*(Assumptions!$B$11/B$5))*Assumptions!$B$15/1000+(Assumptions!$B$27+Assumptions!$B$23)*$A8/1000+Assumptions!$B$29)+Baseline!$B$19)-((Optimized!$B$19*$A8)/Optimized!$B$6+Assumptions!$B$37+Optimized!$B$38) | C8: =(((Assumptions!$B$26*(Assumptions!$B$11/C$5))*Assumptions!$B$15/1000+(Assumptions!$B$27+Assumptions!$B$23)*$A8/1000+Assumptions!$B$29)+Baseline!$B$19)-((Optimized!$B$19*$A8)/Optimized!$B$6+Assumptions!$B$37+Optimized!$B$38) | D8: =(((Assumptions!$B$26*(Assumptions!$B$11/D$5))*Assumptions!$B$15/1000+(Assumptions!$B$27+Assumptions!$B$23)*$A8/1000+Assumptions!$B$29)+Baseline!$B$19)-((Optimized!$B$19*$A8)/Optimized!$B$6+Assumptions!$B$37+Optimized!$B$38) | E8: =(((Assumptions!$B$26*(Assumptions!$B$11/E$5))*Assumptions!$B$15/1000+(Assumptions!$B$27+Assumptions!$B$23)*$A8/1000+Assumptions!$B$29)+Baseline!$B$19)-((Optimized!$B$19*$A8)/Optimized!$B$6+Assumptions!$B$37+Optimized!$B$38) | F8: =(((Assumptions!$B$26*(Assumptions!$B$11/F$5))*Assumptions!$B$15/1000+(Assumptions!$B$27+Assumptions!$B$23)*$A8/1000+Assumptions!$B$29)+Baseline!$B$19)-((Optimized!$B$19*$A8)/Optimized!$B$6+Assumptions!$B$37+Optimized!$B$38) | G8: =(((Assumptions!$B$26*(Assumptions!$B$11/G$5))*Assumptions!$B$15/1000+(Assumptions!$B$27+Assumptions!$B$23)*$A8/1000+Assumptions!$B$29)+Baseline!$B$19)-((Optimized!$B$19*$A8)/Optimized!$B$6+Assumptions!$B$37+Optimized!$B$38)
A9: 120 | B9: =(((Assumptions!$B$26*(Assumptions!$B$11/B$5))*Assumptions!$B$15/1000+(Assumptions!$B$27+Assumptions!$B$23)*$A9/1000+Assumptions!$B$29)+Baseline!$B$19)-((Optimized!$B$19*$A9)/Optimized!$B$6+Assumptions!$B$37+Optimized!$B$38) | C9: =(((Assumptions!$B$26*(Assumptions!$B$11/C$5))*Assumptions!$B$15/1000+(Assumptions!$B$27+Assumptions!$B$23)*$A9/1000+Assumptions!$B$29)+Baseline!$B$19)-((Optimized!$B$19*$A9)/Optimized!$B$6+Assumptions!$B$37+Optimized!$B$38) | D9: =(((Assumptions!$B$26*(Assumptions!$B$11/D$5))*Assumptions!$B$15/1000+(Assumptions!$B$27+Assumptions!$B$23)*$A9/1000+Assumptions!$B$29)+Baseline!$B$19)-((Optimized!$B$19*$A9)/Optimized!$B$6+Assumptions!$B$37+Optimized!$B$38) | E9: =(((Assumptions!$B$26*(Assumptions!$B$11/E$5))*Assumptions!$B$15/1000+(Assumptions!$B$27+Assumptions!$B$23)*$A9/1000+Assumptions!$B$29)+Baseline!$B$19)-((Optimized!$B$19*$A9)/Optimized!$B$6+Assumptions!$B$37+Optimized!$B$38) | F9: =(((Assumptions!$B$26*(Assumptions!$B$11/F$5))*Assumptions!$B$15/1000+(Assumptions!$B$27+Assumptions!$B$23)*$A9/1000+Assumptions!$B$29)+Baseline!$B$19)-((Optimized!$B$19*$A9)/Optimized!$B$6+Assumptions!$B$37+Optimized!$B$38) | G9: =(((Assumptions!$B$26*(Assumptions!$B$11/G$5))*Assumptions!$B$15/1000+(Assumptions!$B$27+Assumptions!$B$23)*$A9/1000+Assumptions!$B$29)+Baseline!$B$19)-((Optimized!$B$19*$A9)/Optimized!$B$6+Assumptions!$B$37+Optimized!$B$38)
A10: 140 | B10: =(((Assumptions!$B$26*(Assumptions!$B$11/B$5))*Assumptions!$B$15/1000+(Assumptions!$B$27+Assumptions!$B$23)*$A10/1000+Assumptions!$B$29)+Baseline!$B$19)-((Optimized!$B$19*$A10)/Optimized!$B$6+Assumptions!$B$37+Optimized!$B$38) | C10: =(((Assumptions!$B$26*(Assumptions!$B$11/C$5))*Assumptions!$B$15/1000+(Assumptions!$B$27+Assumptions!$B$23)*$A10/1000+Assumptions!$B$29)+Baseline!$B$19)-((Optimized!$B$19*$A10)/Optimized!$B$6+Assumptions!$B$37+Optimized!$B$38) | D10: =(((Assumptions!$B$26*(Assumptions!$B$11/D$5))*Assumptions!$B$15/1000+(Assumptions!$B$27+Assumptions!$B$23)*$A10/1000+Assumptions!$B$29)+Baseline!$B$19)-((Optimized!$B$19*$A10)/Optimized!$B$6+Assumptions!$B$37+Optimized!$B$38) | E10: =(((Assumptions!$B$26*(Assumptions!$B$11/E$5))*Assumptions!$B$15/1000+(Assumptions!$B$27+Assumptions!$B$23)*$A10/1000+Assumptions!$B$29)+Baseline!$B$19)-((Optimized!$B$19*$A10)/Optimized!$B$6+Assumptions!$B$37+Optimized!$B$38) | F10: =(((Assumptions!$B$26*(Assumptions!$B$11/F$5))*Assumptions!$B$15/1000+(Assumptions!$B$27+Assumptions!$B$23)*$A10/1000+Assumptions!$B$29)+Baseline!$B$19)-((Optimized!$B$19*$A10)/Optimized!$B$6+Assumptions!$B$37+Optimized!$B$38) | G10: =(((Assumptions!$B$26*(Assumptions!$B$11/G$5))*Assumptions!$B$15/1000+(Assumptions!$B$27+Assumptions!$B$23)*$A10/1000+Assumptions!$B$29)+Baseline!$B$19)-((Optimized!$B$19*$A10)/Optimized!$B$6+Assumptions!$B$37+Optimized!$B$38)
A11: 160 | B11: =(((Assumptions!$B$26*(Assumptions!$B$11/B$5))*Assumptions!$B$15/1000+(Assumptions!$B$27+Assumptions!$B$23)*$A11/1000+Assumptions!$B$29)+Baseline!$B$19)-((Optimized!$B$19*$A11)/Optimized!$B$6+Assumptions!$B$37+Optimized!$B$38) | C11: =(((Assumptions!$B$26*(Assumptions!$B$11/C$5))*Assumptions!$B$15/1000+(Assumptions!$B$27+Assumptions!$B$23)*$A11/1000+Assumptions!$B$29)+Baseline!$B$19)-((Optimized!$B$19*$A11)/Optimized!$B$6+Assumptions!$B$37+Optimized!$B$38) | D11: =(((Assumptions!$B$26*(Assumptions!$B$11/D$5))*Assumptions!$B$15/1000+(Assumptions!$B$27+Assumptions!$B$23)*$A11/1000+Assumptions!$B$29)+Baseline!$B$19)-((Optimized!$B$19*$A11)/Optimized!$B$6+Assumptions!$B$37+Optimized!$B$38) | E11: =(((Assumptions!$B$26*(Assumptions!$B$11/E$5))*Assumptions!$B$15/1000+(Assumptions!$B$27+Assumptions!$B$23)*$A11/1000+Assumptions!$B$29)+Baseline!$B$19)-((Optimized!$B$19*$A11)/Optimized!$B$6+Assumptions!$B$37+Optimized!$B$38) | F11: =(((Assumptions!$B$26*(Assumptions!$B$11/F$5))*Assumptions!$B$15/1000+(Assumptions!$B$27+Assumptions!$B$23)*$A11/1000+Assumptions!$B$29)+Baseline!$B$19)-((Optimized!$B$19*$A11)/Optimized!$B$6+Assumptions!$B$37+Optimized!$B$38) | G11: =(((Assumptions!$B$26*(Assumptions!$B$11/G$5))*Assumptions!$B$15/1000+(Assumptions!$B$27+Assumptions!$B$23)*$A11/1000+Assumptions!$B$29)+Baseline!$B$19)-((Optimized!$B$19*$A11)/Optimized!$B$6+Assumptions!$B$37+Optimized!$B$38)
A12: 180 | B12: =(((Assumptions!$B$26*(Assumptions!$B$11/B$5))*Assumptions!$B$15/1000+(Assumptions!$B$27+Assumptions!$B$23)*$A12/1000+Assumptions!$B$29)+Baseline!$B$19)-((Optimized!$B$19*$A12)/Optimized!$B$6+Assumptions!$B$37+Optimized!$B$38) | C12: =(((Assumptions!$B$26*(Assumptions!$B$11/C$5))*Assumptions!$B$15/1000+(Assumptions!$B$27+Assumptions!$B$23)*$A12/1000+Assumptions!$B$29)+Baseline!$B$19)-((Optimized!$B$19*$A12)/Optimized!$B$6+Assumptions!$B$37+Optimized!$B$38) | D12: =(((Assumptions!$B$26*(Assumptions!$B$11/D$5))*Assumptions!$B$15/1000+(Assumptions!$B$27+Assumptions!$B$23)*$A12/1000+Assumptions!$B$29)+Baseline!$B$19)-((Optimized!$B$19*$A12)/Optimized!$B$6+Assumptions!$B$37+Optimized!$B$38) | E12: =(((Assumptions!$B$26*(Assumptions!$B$11/E$5))*Assumptions!$B$15/1000+(Assumptions!$B$27+Assumptions!$B$23)*$A12/1000+Assumptions!$B$29)+Baseline!$B$19)-((Optimized!$B$19*$A12)/Optimized!$B$6+Assumptions!$B$37+Optimized!$B$38) | F12: =(((Assumptions!$B$26*(Assumptions!$B$11/F$5))*Assumptions!$B$15/1000+(Assumptions!$B$27+Assumptions!$B$23)*$A12/1000+Assumptions!$B$29)+Baseline!$B$19)-((Optimized!$B$19*$A12)/Optimized!$B$6+Assumptions!$B$37+Optimized!$B$38) | G12: =(((Assumptions!$B$26*(Assumptions!$B$11/G$5))*Assumptions!$B$15/1000+(Assumptions!$B$27+Assumptions!$B$23)*$A12/1000+Assumptions!$B$29)+Baseline!$B$19)-((Optimized!$B$19*$A12)/Optimized!$B$6+Assumptions!$B$37+Optimized!$B$38)
A15: TABLE 2 — Optimized all-in £/t vs O2 demand ratio and ASU specific energy (robustness check on the least-certain oxy-fuel inputs)
A16: O2 ratio \ ASU kWh/t | B16: 250 | C16: 300 | D16: 350 | E16: 400 | F16: 450
A17: 0.2 | B17: =(((MAX(0,((($A17*B$16)+Assumptions!$B$35+Assumptions!$B$23)*Optimized!$B$6/1000)-Optimized!$B$18)*Assumptions!$B$14)+(Assumptions!$B$37*Optimized!$B$6))/Optimized!$B$6)+(((((Assumptions!$B$34*($A17*Optimized!$B$6))+Optimized!$B$30+Optimized!$B$31+Optimized!$B$32)-Optimized!$B$34)*Optimized!$B$36)/Optimized!$B$6) | C17: =(((MAX(0,((($A17*C$16)+Assumptions!$B$35+Assumptions!$B$23)*Optimized!$B$6/1000)-Optimized!$B$18)*Assumptions!$B$14)+(Assumptions!$B$37*Optimized!$B$6))/Optimized!$B$6)+(((((Assumptions!$B$34*($A17*Optimized!$B$6))+Optimized!$B$30+Optimized!$B$31+Optimized!$B$32)-Optimized!$B$34)*Optimized!$B$36)/Optimized!$B$6) | D17: =(((MAX(0,((($A17*D$16)+Assumptions!$B$35+Assumptions!$B$23)*Optimized!$B$6/1000)-Optimized!$B$18)*Assumptions!$B$14)+(Assumptions!$B$37*Optimized!$B$6))/Optimized!$B$6)+(((((Assumptions!$B$34*($A17*Optimized!$B$6))+Optimized!$B$30+Optimized!$B$31+Optimized!$B$32)-Optimized!$B$34)*Optimized!$B$36)/Optimized!$B$6) | E17: =(((MAX(0,((($A17*E$16)+Assumptions!$B$35+Assumptions!$B$23)*Optimized!$B$6/1000)-Optimized!$B$18)*Assumptions!$B$14)+(Assumptions!$B$37*Optimized!$B$6))/Optimized!$B$6)+(((((Assumptions!$B$34*($A17*Optimized!$B$6))+Optimized!$B$30+Optimized!$B$31+Optimized!$B$32)-Optimized!$B$34)*Optimized!$B$36)/Optimized!$B$6) | F17: =(((MAX(0,((($A17*F$16)+Assumptions!$B$35+Assumptions!$B$23)*Optimized!$B$6/1000)-Optimized!$B$18)*Assumptions!$B$14)+(Assumptions!$B$37*Optimized!$B$6))/Optimized!$B$6)+(((((Assumptions!$B$34*($A17*Optimized!$B$6))+Optimized!$B$30+Optimized!$B$31+Optimized!$B$32)-Optimized!$B$34)*Optimized!$B$36)/Optimized!$B$6)
A18: 0.25 | B18: =(((MAX(0,((($A18*B$16)+Assumptions!$B$35+Assumptions!$B$23)*Optimized!$B$6/1000)-Optimized!$B$18)*Assumptions!$B$14)+(Assumptions!$B$37*Optimized!$B$6))/Optimized!$B$6)+(((((Assumptions!$B$34*($A18*Optimized!$B$6))+Optimized!$B$30+Optimized!$B$31+Optimized!$B$32)-Optimized!$B$34)*Optimized!$B$36)/Optimized!$B$6) | C18: =(((MAX(0,((($A18*C$16)+Assumptions!$B$35+Assumptions!$B$23)*Optimized!$B$6/1000)-Optimized!$B$18)*Assumptions!$B$14)+(Assumptions!$B$37*Optimized!$B$6))/Optimized!$B$6)+(((((Assumptions!$B$34*($A18*Optimized!$B$6))+Optimized!$B$30+Optimized!$B$31+Optimized!$B$32)-Optimized!$B$34)*Optimized!$B$36)/Optimized!$B$6) | D18: =(((MAX(0,((($A18*D$16)+Assumptions!$B$35+Assumptions!$B$23)*Optimized!$B$6/1000)-Optimized!$B$18)*Assumptions!$B$14)+(Assumptions!$B$37*Optimized!$B$6))/Optimized!$B$6)+(((((Assumptions!$B$34*($A18*Optimized!$B$6))+Optimized!$B$30+Optimized!$B$31+Optimized!$B$32)-Optimized!$B$34)*Optimized!$B$36)/Optimized!$B$6) | E18: =(((MAX(0,((($A18*E$16)+Assumptions!$B$35+Assumptions!$B$23)*Optimized!$B$6/1000)-Optimized!$B$18)*Assumptions!$B$14)+(Assumptions!$B$37*Optimized!$B$6))/Optimized!$B$6)+(((((Assumptions!$B$34*($A18*Optimized!$B$6))+Optimized!$B$30+Optimized!$B$31+Optimized!$B$32)-Optimized!$B$34)*Optimized!$B$36)/Optimized!$B$6) | F18: =(((MAX(0,((($A18*F$16)+Assumptions!$B$35+Assumptions!$B$23)*Optimized!$B$6/1000)-Optimized!$B$18)*Assumptions!$B$14)+(Assumptions!$B$37*Optimized!$B$6))/Optimized!$B$6)+(((((Assumptions!$B$34*($A18*Optimized!$B$6))+Optimized!$B$30+Optimized!$B$31+Optimized!$B$32)-Optimized!$B$34)*Optimized!$B$36)/Optimized!$B$6)
A19: 0.3 | B19: =(((MAX(0,((($A19*B$16)+Assumptions!$B$35+Assumptions!$B$23)*Optimized!$B$6/1000)-Optimized!$B$18)*Assumptions!$B$14)+(Assumptions!$B$37*Optimized!$B$6))/Optimized!$B$6)+(((((Assumptions!$B$34*($A19*Optimized!$B$6))+Optimized!$B$30+Optimized!$B$31+Optimized!$B$32)-Optimized!$B$34)*Optimized!$B$36)/Optimized!$B$6) | C19: =(((MAX(0,((($A19*C$16)+Assumptions!$B$35+Assumptions!$B$23)*Optimized!$B$6/1000)-Optimized!$B$18)*Assumptions!$B$14)+(Assumptions!$B$37*Optimized!$B$6))/Optimized!$B$6)+(((((Assumptions!$B$34*($A19*Optimized!$B$6))+Optimized!$B$30+Optimized!$B$31+Optimized!$B$32)-Optimized!$B$34)*Optimized!$B$36)/Optimized!$B$6) | D19: =(((MAX(0,((($A19*D$16)+Assumptions!$B$35+Assumptions!$B$23)*Optimized!$B$6/1000)-Optimized!$B$18)*Assumptions!$B$14)+(Assumptions!$B$37*Optimized!$B$6))/Optimized!$B$6)+(((((Assumptions!$B$34*($A19*Optimized!$B$6))+Optimized!$B$30+Optimized!$B$31+Optimized!$B$32)-Optimized!$B$34)*Optimized!$B$36)/Optimized!$B$6) | E19: =(((MAX(0,((($A19*E$16)+Assumptions!$B$35+Assumptions!$B$23)*Optimized!$B$6/1000)-Optimized!$B$18)*Assumptions!$B$14)+(Assumptions!$B$37*Optimized!$B$6))/Optimized!$B$6)+(((((Assumptions!$B$34*($A19*Optimized!$B$6))+Optimized!$B$30+Optimized!$B$31+Optimized!$B$32)-Optimized!$B$34)*Optimized!$B$36)/Optimized!$B$6) | F19: =(((MAX(0,((($A19*F$16)+Assumptions!$B$35+Assumptions!$B$23)*Optimized!$B$6/1000)-Optimized!$B$18)*Assumptions!$B$14)+(Assumptions!$B$37*Optimized!$B$6))/Optimized!$B$6)+(((((Assumptions!$B$34*($A19*Optimized!$B$6))+Optimized!$B$30+Optimized!$B$31+Optimized!$B$32)-Optimized!$B$34)*Optimized!$B$36)/Optimized!$B$6)
A20: 0.35 | B20: =(((MAX(0,((($A20*B$16)+Assumptions!$B$35+Assumptions!$B$23)*Optimized!$B$6/1000)-Optimized!$B$18)*Assumptions!$B$14)+(Assumptions!$B$37*Optimized!$B$6))/Optimized!$B$6)+(((((Assumptions!$B$34*($A20*Optimized!$B$6))+Optimized!$B$30+Optimized!$B$31+Optimized!$B$32)-Optimized!$B$34)*Optimized!$B$36)/Optimized!$B$6) | C20: =(((MAX(0,((($A20*C$16)+Assumptions!$B$35+Assumptions!$B$23)*Optimized!$B$6/1000)-Optimized!$B$18)*Assumptions!$B$14)+(Assumptions!$B$37*Optimized!$B$6))/Optimized!$B$6)+(((((Assumptions!$B$34*($A20*Optimized!$B$6))+Optimized!$B$30+Optimized!$B$31+Optimized!$B$32)-Optimized!$B$34)*Optimized!$B$36)/Optimized!$B$6) | D20: =(((MAX(0,((($A20*D$16)+Assumptions!$B$35+Assumptions!$B$23)*Optimized!$B$6/1000)-Optimized!$B$18)*Assumptions!$B$14)+(Assumptions!$B$37*Optimized!$B$6))/Optimized!$B$6)+(((((Assumptions!$B$34*($A20*Optimized!$B$6))+Optimized!$B$30+Optimized!$B$31+Optimized!$B$32)-Optimized!$B$34)*Optimized!$B$36)/Optimized!$B$6) | E20: =(((MAX(0,((($A20*E$16)+Assumptions!$B$35+Assumptions!$B$23)*Optimized!$B$6/1000)-Optimized!$B$18)*Assumptions!$B$14)+(Assumptions!$B$37*Optimized!$B$6))/Optimized!$B$6)+(((((Assumptions!$B$34*($A20*Optimized!$B$6))+Optimized!$B$30+Optimized!$B$31+Optimized!$B$32)-Optimized!$B$34)*Optimized!$B$36)/Optimized!$B$6) | F20: =(((MAX(0,((($A20*F$16)+Assumptions!$B$35+Assumptions!$B$23)*Optimized!$B$6/1000)-Optimized!$B$18)*Assumptions!$B$14)+(Assumptions!$B$37*Optimized!$B$6))/Optimized!$B$6)+(((((Assumptions!$B$34*($A20*Optimized!$B$6))+Optimized!$B$30+Optimized!$B$31+Optimized!$B$32)-Optimized!$B$34)*Optimized!$B$36)/Optimized!$B$6)
A21: 0.4 | B21: =(((MAX(0,((($A21*B$16)+Assumptions!$B$35+Assumptions!$B$23)*Optimized!$B$6/1000)-Optimized!$B$18)*Assumptions!$B$14)+(Assumptions!$B$37*Optimized!$B$6))/Optimized!$B$6)+(((((Assumptions!$B$34*($A21*Optimized!$B$6))+Optimized!$B$30+Optimized!$B$31+Optimized!$B$32)-Optimized!$B$34)*Optimized!$B$36)/Optimized!$B$6) | C21: =(((MAX(0,((($A21*C$16)+Assumptions!$B$35+Assumptions!$B$23)*Optimized!$B$6/1000)-Optimized!$B$18)*Assumptions!$B$14)+(Assumptions!$B$37*Optimized!$B$6))/Optimized!$B$6)+(((((Assumptions!$B$34*($A21*Optimized!$B$6))+Optimized!$B$30+Optimized!$B$31+Optimized!$B$32)-Optimized!$B$34)*Optimized!$B$36)/Optimized!$B$6) | D21: =(((MAX(0,((($A21*D$16)+Assumptions!$B$35+Assumptions!$B$23)*Optimized!$B$6/1000)-Optimized!$B$18)*Assumptions!$B$14)+(Assumptions!$B$37*Optimized!$B$6))/Optimized!$B$6)+(((((Assumptions!$B$34*($A21*Optimized!$B$6))+Optimized!$B$30+Optimized!$B$31+Optimized!$B$32)-Optimized!$B$34)*Optimized!$B$36)/Optimized!$B$6) | E21: =(((MAX(0,((($A21*E$16)+Assumptions!$B$35+Assumptions!$B$23)*Optimized!$B$6/1000)-Optimized!$B$18)*Assumptions!$B$14)+(Assumptions!$B$37*Optimized!$B$6))/Optimized!$B$6)+(((((Assumptions!$B$34*($A21*Optimized!$B$6))+Optimized!$B$30+Optimized!$B$31+Optimized!$B$32)-Optimized!$B$34)*Optimized!$B$36)/Optimized!$B$6) | F21: =(((MAX(0,((($A21*F$16)+Assumptions!$B$35+Assumptions!$B$23)*Optimized!$B$6/1000)-Optimized!$B$18)*Assumptions!$B$14)+(Assumptions!$B$37*Optimized!$B$6))/Optimized!$B$6)+(((((Assumptions!$B$34*($A21*Optimized!$B$6))+Optimized!$B$30+Optimized!$B$31+Optimized!$B$32)-Optimized!$B$34)*Optimized!$B$36)/Optimized!$B$6)
A24: Read Table 1 as: darker/lower savings cells (top-right, low tariff + concentrated baseline gas) are where the amine baseline is already fairly cheap — the optimized package still wins on WHR insulation, but by less. Table 2 shows the optimized case's own cost is far more sensitive to the O2 ratio (capex-driving) than to ASU efficiency alone — that mass-balance assumption is the one to pin down first with an engineering study.
